cos_alerter/alerter.py
cos_alerter/config-defaults.yaml
cos_alerter/daemon.py
cos_alerter/logging.py
cos_alerter/server.py
cos_alerter/static/vanilla-framework-version-3.14.0.min.css
cos_alerter/templates/dashboard.html
cos_alerter-0.9.0.dist-info/LICENSE
cos_alerter-0.9.0.dist-info/METADATA
cos_alerter-0.9.0.dist-info/WHEEL
cos_alerter-0.9.0.dist-info/entry_points.txt
cos_alerter-0.9.0.dist-info/top_level.txt
cos_alerter-0.9.0.dist-info/RECORD
