Metadata-Version: 2.1
Name: cos-alerter
Version: 0.9.0
Summary: A watcher for Alertmanager
Author-email: Dylan Stephano-Shachter <dylan.stephano-shachter@canonical.com>
Project-URL: Homepage, https://github.com/canonical/cos-alerter
Project-URL: Bug Tracker, https://github.com/canonical/cos-alerter/issues
Classifier: Programming Language :: Python
Classifier: License :: OSI Approved :: Apache Software License
Classifier: Operating System :: POSIX
Classifier: Topic :: System :: Monitoring
Classifier: Development Status :: 3 - Alpha
Requires-Python: >=3.8
License-File: LICENSE
Requires-Dist: apprise ~=1.3
Requires-Dist: durationpy
Requires-Dist: flask ~=2.2
Requires-Dist: prometheus-flask-exporter ~=0.22
Requires-Dist: pyyaml ~=6.0
Requires-Dist: ruamel.yaml ~=0.18.0
Requires-Dist: timeago ~=1.0
Requires-Dist: waitress ~=2.1
Requires-Dist: xdg-base-dirs ~=6.0.1
Requires-Dist: pdpyras ~=5.2.0
